Metadata-Version: 2.4
Name: llama_voice-llamasearch
Version: 0.1.0
Summary: On-device voice processing pipeline for fast, private voice interaction
Home-page: https://llamasearch.ai
Author: LlamaSearch AI
Author-email: llama_voice-llamasearch <nikjois@llamasearch.ai>
License: MIT
Classifier: Development Status :: 4 - Beta
Classifier: Intended Audience :: Developers
Classifier: License :: OSI Approved :: MIT License
Classifier: Programming Language :: Python :: 3
Classifier: Programming Language :: Python :: 3.8
Classifier: Programming Language :: Python :: 3.9
Classifier: Programming Language :: Python :: 3.10
Classifier: Programming Language :: Python :: 3.11
Classifier: Topic :: Software Development :: Libraries :: Python Modules
Classifier: Topic :: Multimedia :: Sound/Audio :: Speech
Requires-Python: >=3.8
License-File: LICENSE
Requires-Dist: numpy>=1.20.0
Requires-Dist: scipy>=1.7.0
Requires-Dist: tqdm>=4.62.0
Dynamic: author
Dynamic: home-page
Dynamic: license-file
Dynamic: requires-python
